power_slides/__init__.py
power_slides/cli.py
power_slides/generator.py
power_slides/parser.py
power_slides/presentation_template.html
power_slides/layouts/50-50.py
power_slides-0.1.4.dist-info/licenses/LICENSE
power_slides-0.1.4.dist-info/METADATA
power_slides-0.1.4.dist-info/WHEEL
power_slides-0.1.4.dist-info/entry_points.txt
power_slides-0.1.4.dist-info/top_level.txt
power_slides-0.1.4.dist-info/RECORD
