Metadata-Version: 2.4
Name: power-slides
Version: 0.1.4
Summary: A tool to generate HTML presentations from Markdown.
Author-email: rajxsingh <rajbir@live.de>
License-Expression: MIT
Project-URL: homepage, https://github.com/rajxsingh/power-slides
Project-URL: repository, https://github.com/rajxsingh/power-slides
License-File: LICENSE
Requires-Dist: PyYAML
Dynamic: license-file
